pyromark-0.9.7.dist-info/METADATA
pyromark-0.9.7.dist-info/WHEEL
pyromark-0.9.7.dist-info/entry_points.txt
pyromark-0.9.7.dist-info/licenses/LICENSE
pyromark/__init__.py
pyromark/__main__.py
pyromark/_cli.py
pyromark/_options.py
pyromark/_pyromark.pyi
pyromark/_pyromark.pypy311-pp73-x86_64-linux-gnu.so
pyromark/event.py
pyromark/py.typed
pyromark-0.9.7.dist-info/RECORD
