Metadata-Version: 2.4
Name: pyromark
Version: 0.9.7
Classifier: Natural Language :: English
Classifier: Operating System :: MacOS
Classifier: Operating System :: Microsoft :: Windows
Classifier: Operating System :: POSIX :: Linux
Classifier: Programming Language :: Python
Classifier: Programming Language :: Python :: 3 :: Only
Classifier: Programming Language :: Python :: 3.9
Classifier: Programming Language :: Python :: 3.10
Classifier: Programming Language :: Python :: 3.11
Classifier: Programming Language :: Python :: 3.12
Classifier: Programming Language :: Python :: 3.13
Classifier: Programming Language :: Python :: 3.14
Classifier: Programming Language :: Python :: Implementation :: CPython
Classifier: Programming Language :: Python :: Implementation :: PyPy
Classifier: Programming Language :: Rust
Classifier: Typing :: Typed
Requires-Dist: typing-extensions>=3.7.4.2
License-File: LICENSE
Summary: Blazingly fast Markdown parser
Keywords: converter,html
Author-email: monosans <hsyqixco@protonmail.com>
Requires-Python: >=3.9
Project-URL: documentation, https://pyromark.readthedocs.io
Project-URL: repository, https://github.com/monosans/pyromark
